[
  {
    "FileName": "IMG_3090.JPEG",
    "FilePath": "IMG_3090.JPEG",
    "FileSize": 2306800,
    "Latitude": 54.577075,
    "Longitude": -2.930194444444444,
    "Altitude": "197.61 metres",
    "City": "Dockray",
    "State": "England",
    "Country": "United Kingdom",
    "CountryCode": "GB",
    "DisplayName": "Park Brow, Matterdale, Dockray, Westmorland and Furness, England, CA11 0JY, United Kingdom",
    "Region": "Westmorland and Furness",
    "CameraMake": "Apple",
    "CameraModel": "iPhone 15 Pro",
    "LensModel": "iPhone 15 Pro back triple camera 6.765mm f/1.78",
    "DateTaken": "2026:01:12 12:02:31",
    "ExposureTime": "1/158 sec",
    "FNumber": "f/1.8",
    "ISO": "64",
    "FocalLength": "6.8 mm",
    "Orientation": "Top, left side (Horizontal / normal)",
    "Software": "26.2",
    "OptimizedImages": {
      "WebPImage": "1b340156b0757178.webp",
      "OriginalSize": 2306800,
      "OptimizedSize": 1104936,
      "CompressionRatio": 52.100919022021856
    },
    "HasGpsData": true
  },
  {
    "FileName": "IMG_3089.JPEG",
    "FilePath": "IMG_3089.JPEG",
    "FileSize": 2123180,
    "Latitude": 54.577075,
    "Longitude": -2.9301916666666665,
    "Altitude": "197.36 metres",
    "City": "Dockray",
    "State": "England",
    "Country": "United Kingdom",
    "CountryCode": "GB",
    "DisplayName": "Park Brow, Matterdale, Dockray, Westmorland and Furness, England, CA11 0JY, United Kingdom",
    "Region": "Westmorland and Furness",
    "CameraMake": "Apple",
    "CameraModel": "iPhone 15 Pro",
    "LensModel": "iPhone 15 Pro back triple camera 2.22mm f/2.2",
    "DateTaken": "2026:01:12 12:02:28",
    "ExposureTime": "1/99 sec",
    "FNumber": "f/2.2",
    "ISO": "50",
    "FocalLength": "2.2 mm",
    "Software": "26.2",
    "OptimizedImages": {
      "WebPImage": "92ffd53ee815c544.webp",
      "OriginalSize": 2123180,
      "OptimizedSize": 995852,
      "CompressionRatio": 53.09620474947956
    },
    "HasGpsData": true
  },
  {
    "FileName": "IMG_3087.JPEG",
    "FilePath": "IMG_3087.JPEG",
    "FileSize": 2162198,
    "Latitude": 54.57696111111112,
    "Longitude": -2.930247222222222,
    "Altitude": "195.74 metres",
    "City": "Dockray",
    "State": "England",
    "Country": "United Kingdom",
    "CountryCode": "GB",
    "DisplayName": "Park Brow, Matterdale, Dockray, Westmorland and Furness, England, CA11 0JY, United Kingdom",
    "Region": "Westmorland and Furness",
    "CameraMake": "Apple",
    "CameraModel": "iPhone 15 Pro",
    "LensModel": "iPhone 15 Pro back triple camera 2.22mm f/2.2",
    "DateTaken": "2026:01:12 12:01:29",
    "ExposureTime": "1/99 sec",
    "FNumber": "f/2.2",
    "ISO": "64",
    "FocalLength": "2.2 mm",
    "Orientation": "Top, left side (Horizontal / normal)",
    "Software": "26.2",
    "OptimizedImages": {
      "WebPImage": "43f05f0daf3d114d.webp",
      "OriginalSize": 2162198,
      "OptimizedSize": 1003424,
      "CompressionRatio": 53.59240920581742
    },
    "HasGpsData": true
  },
  {
    "FileName": "IMG_3085.JPEG",
    "FilePath": "IMG_3085.JPEG",
    "FileSize": 2004182,
    "Latitude": 54.576636111111114,
    "Longitude": -2.930622222222222,
    "Altitude": "199.1 metres",
    "City": "Dockray",
    "State": "England",
    "Country": "United Kingdom",
    "CountryCode": "GB",
    "DisplayName": "Park Brow, Matterdale, Dockray, Westmorland and Furness, England, CA11 0JY, United Kingdom",
    "Region": "Westmorland and Furness",
    "CameraMake": "Apple",
    "CameraModel": "iPhone 15 Pro",
    "LensModel": "iPhone 15 Pro back triple camera 2.22mm f/2.2",
    "DateTaken": "2026:01:12 11:58:37",
    "ExposureTime": "1/99 sec",
    "FNumber": "f/2.2",
    "ISO": "80",
    "FocalLength": "2.2 mm",
    "Orientation": "Top, left side (Horizontal / normal)",
    "Software": "26.2",
    "OptimizedImages": {
      "WebPImage": "4695c32c5481f6e3.webp",
      "OriginalSize": 2004182,
      "OptimizedSize": 962764,
      "CompressionRatio": 51.96224694164502
    },
    "HasGpsData": true
  },
  {
    "FileName": "IMG_3084.JPEG",
    "FilePath": "IMG_3084.JPEG",
    "FileSize": 1932545,
    "Latitude": 54.57664444444445,
    "Longitude": -2.9305749999999997,
    "Altitude": "197.81 metres",
    "City": "Dockray",
    "State": "England",
    "Country": "United Kingdom",
    "CountryCode": "GB",
    "DisplayName": "Park Brow, Matterdale, Dockray, Westmorland and Furness, England, CA11 0JY, United Kingdom",
    "Region": "Westmorland and Furness",
    "CameraMake": "Apple",
    "CameraModel": "iPhone 15 Pro",
    "LensModel": "iPhone 15 Pro back triple camera 2.22mm f/2.2",
    "DateTaken": "2026:01:12 11:58:24",
    "ExposureTime": "1/109 sec",
    "FNumber": "f/2.2",
    "ISO": "40",
    "FocalLength": "2.2 mm",
    "Software": "26.2",
    "OptimizedImages": {
      "WebPImage": "bd98aade55b57db6.webp",
      "OriginalSize": 1932545,
      "OptimizedSize": 878270,
      "CompressionRatio": 54.553710262891684
    },
    "HasGpsData": true
  },
  {
    "FileName": "IMG_3083.JPEG",
    "FilePath": "IMG_3083.JPEG",
    "FileSize": 2274545,
    "Latitude": 54.57678888888889,
    "Longitude": -2.9302249999999996,
    "Altitude": "198.74 metres",
    "City": "Dockray",
    "State": "England",
    "Country": "United Kingdom",
    "CountryCode": "GB",
    "DisplayName": "Park Brow, Matterdale, Dockray, Westmorland and Furness, England, CA11 0JY, United Kingdom",
    "Region": "Westmorland and Furness",
    "CameraMake": "Apple",
    "CameraModel": "iPhone 15 Pro",
    "LensModel": "iPhone 15 Pro back triple camera 2.22mm f/2.2",
    "DateTaken": "2026:01:12 11:56:19",
    "ExposureTime": "1/134 sec",
    "FNumber": "f/2.2",
    "ISO": "40",
    "FocalLength": "2.2 mm",
    "Software": "26.2",
    "OptimizedImages": {
      "WebPImage": "fb9ec95d3d575bc9.webp",
      "OriginalSize": 2274545,
      "OptimizedSize": 1053792,
      "CompressionRatio": 53.670206568786284
    },
    "HasGpsData": true
  },
  {
    "FileName": "IMG_3082.JPEG",
    "FilePath": "IMG_3082.JPEG",
    "FileSize": 2163309,
    "Latitude": 54.57636388888889,
    "Longitude": -2.9307222222222222,
    "Altitude": "196.09 metres",
    "City": "Dockray",
    "State": "England",
    "Country": "United Kingdom",
    "CountryCode": "GB",
    "DisplayName": "Park Brow, Matterdale, Dockray, Westmorland and Furness, England, CA11 0JY, United Kingdom",
    "Region": "Westmorland and Furness",
    "CameraMake": "Apple",
    "CameraModel": "iPhone 15 Pro",
    "LensModel": "iPhone 15 Pro back triple camera 6.765mm f/1.78",
    "DateTaken": "2026:01:12 11:53:52",
    "ExposureTime": "1/72 sec",
    "FNumber": "f/1.8",
    "ISO": "100",
    "FocalLength": "6.8 mm",
    "Software": "26.2",
    "OptimizedImages": {
      "WebPImage": "2a39dbe4bb637508.webp",
      "OriginalSize": 2163309,
      "OptimizedSize": 1004596,
      "CompressionRatio": 53.5620662605296
    },
    "HasGpsData": true
  },
  {
    "FileName": "IMG_3079.JPEG",
    "FilePath": "IMG_3079.JPEG",
    "FileSize": 1834092,
    "Latitude": 54.57626666666667,
    "Longitude": -2.9308638888888887,
    "Altitude": "194.84 metres",
    "City": "Dockray",
    "State": "England",
    "Country": "United Kingdom",
    "CountryCode": "GB",
    "DisplayName": "Park Brow, Matterdale, Dockray, Westmorland and Furness, England, CA11 0JY, United Kingdom",
    "Region": "Westmorland and Furness",
    "CameraMake": "Apple",
    "CameraModel": "iPhone 15 Pro",
    "LensModel": "iPhone 15 Pro back triple camera 2.22mm f/2.2",
    "DateTaken": "2026:01:12 11:48:30",
    "ExposureTime": "1/99 sec",
    "FNumber": "f/2.2",
    "ISO": "64",
    "FocalLength": "2.2 mm",
    "Software": "26.2",
    "OptimizedImages": {
      "WebPImage": "76d1692ec26159a6.webp",
      "OriginalSize": 1834092,
      "OptimizedSize": 807400,
      "CompressionRatio": 55.978217014195586
    },
    "HasGpsData": true
  },
  {
    "FileName": "IMG_3078.JPEG",
    "FilePath": "IMG_3078.JPEG",
    "FileSize": 1392494,
    "Latitude": 54.57624444444445,
    "Longitude": -2.9308527777777775,
    "Altitude": "195.08 metres",
    "City": "Dockray",
    "State": "England",
    "Country": "United Kingdom",
    "CountryCode": "GB",
    "DisplayName": "Park Brow, Matterdale, Dockray, Westmorland and Furness, England, CA11 0JY, United Kingdom",
    "Region": "Westmorland and Furness",
    "CameraMake": "Apple",
    "CameraModel": "iPhone 15 Pro",
    "LensModel": "iPhone 15 Pro back triple camera 6.765mm f/1.78",
    "DateTaken": "2026:01:12 11:48:17",
    "ExposureTime": "1/170 sec",
    "FNumber": "f/1.8",
    "ISO": "50",
    "FocalLength": "6.8 mm",
    "Software": "26.2",
    "OptimizedImages": {
      "WebPImage": "8b6ff5989eab73b6.webp",
      "OriginalSize": 1392494,
      "OptimizedSize": 505400,
      "CompressionRatio": 63.70540914359415
    },
    "HasGpsData": true
  },
  {
    "FileName": "IMG_3077.JPEG",
    "FilePath": "IMG_3077.JPEG",
    "FileSize": 1569625,
    "Latitude": 54.576394444444446,
    "Longitude": -2.9308888888888887,
    "Altitude": "195.88 metres",
    "City": "Dockray",
    "State": "England",
    "Country": "United Kingdom",
    "CountryCode": "GB",
    "DisplayName": "Park Brow, Matterdale, Dockray, Westmorland and Furness, England, CA11 0JY, United Kingdom",
    "Region": "Westmorland and Furness",
    "CameraMake": "Apple",
    "CameraModel": "iPhone 15 Pro",
    "LensModel": "iPhone 15 Pro back triple camera 6.765mm f/1.78",
    "DateTaken": "2026:01:12 11:47:50",
    "ExposureTime": "1/292 sec",
    "FNumber": "f/1.8",
    "ISO": "80",
    "FocalLength": "6.8 mm",
    "Software": "26.2",
    "OptimizedImages": {
      "WebPImage": "e28d6cd3d081d669.webp",
      "OriginalSize": 1569625,
      "OptimizedSize": 628244,
      "CompressionRatio": 59.97489846300867
    },
    "HasGpsData": true
  },
  {
    "FileName": "IMG_3075.JPEG",
    "FilePath": "IMG_3075.JPEG",
    "FileSize": 1963810,
    "Latitude": 54.57625277777778,
    "Longitude": -2.9310694444444443,
    "Altitude": "197.27 metres",
    "City": "Dockray",
    "State": "England",
    "Country": "United Kingdom",
    "CountryCode": "GB",
    "DisplayName": "Park Brow, Matterdale, Dockray, Westmorland and Furness, England, CA11 0JY, United Kingdom",
    "Region": "Westmorland and Furness",
    "CameraMake": "Apple",
    "CameraModel": "iPhone 15 Pro",
    "LensModel": "iPhone 15 Pro back triple camera 6.765mm f/1.78",
    "DateTaken": "2026:01:12 11:46:49",
    "ExposureTime": "1/210 sec",
    "FNumber": "f/1.8",
    "ISO": "80",
    "FocalLength": "6.8 mm",
    "Orientation": "Top, left side (Horizontal / normal)",
    "Software": "26.2",
    "OptimizedImages": {
      "WebPImage": "0f93736ff2ad826b.webp",
      "OriginalSize": 1963810,
      "OptimizedSize": 900060,
      "CompressionRatio": 54.16766387787006
    },
    "HasGpsData": true
  },
  {
    "FileName": "IMG_3074.JPEG",
    "FilePath": "IMG_3074.JPEG",
    "FileSize": 1369151,
    "Latitude": 54.575813888888895,
    "Longitude": -2.9314999999999998,
    "Altitude": "197.17 metres",
    "City": "Dockray",
    "State": "England",
    "Country": "United Kingdom",
    "CountryCode": "GB",
    "DisplayName": "Park Brow, Matterdale, Dockray, Westmorland and Furness, England, CA11 0JY, United Kingdom",
    "Region": "Westmorland and Furness",
    "CameraMake": "Apple",
    "CameraModel": "iPhone 15 Pro",
    "LensModel": "iPhone 15 Pro back triple camera 6.765mm f/1.78",
    "DateTaken": "2026:01:12 11:44:59",
    "ExposureTime": "1/707 sec",
    "FNumber": "f/1.8",
    "ISO": "80",
    "FocalLength": "6.8 mm",
    "Orientation": "Top, left side (Horizontal / normal)",
    "Software": "26.2",
    "OptimizedImages": {
      "WebPImage": "35d4adbb1c563a14.webp",
      "OriginalSize": 1369151,
      "OptimizedSize": 555526,
      "CompressionRatio": 59.42551259868342
    },
    "HasGpsData": true
  },
  {
    "FileName": "IMG_3073.JPEG",
    "FilePath": "IMG_3073.JPEG",
    "FileSize": 1612921,
    "Latitude": 54.57605277777778,
    "Longitude": -2.9319277777777777,
    "Altitude": "209.22 metres",
    "City": "Dockray",
    "State": "England",
    "Country": "United Kingdom",
    "CountryCode": "GB",
    "DisplayName": "Park Brow, Matterdale, Dockray, Westmorland and Furness, England, CA11 0JY, United Kingdom",
    "Region": "Westmorland and Furness",
    "CameraMake": "Apple",
    "CameraModel": "iPhone 15 Pro",
    "LensModel": "iPhone 15 Pro back triple camera 2.22mm f/2.2",
    "DateTaken": "2026:01:12 11:44:00",
    "ExposureTime": "1/233 sec",
    "FNumber": "f/2.2",
    "ISO": "40",
    "FocalLength": "2.2 mm",
    "Orientation": "Top, left side (Horizontal / normal)",
    "Software": "26.2",
    "OptimizedImages": {
      "WebPImage": "5d2a7a756ce1db0c.webp",
      "OriginalSize": 1612921,
      "OptimizedSize": 696864,
      "CompressionRatio": 56.79490812011252
    },
    "HasGpsData": true
  },
  {
    "FileName": "IMG_3072.JPEG",
    "FilePath": "IMG_3072.JPEG",
    "FileSize": 1341077,
    "Latitude": 54.57607222222222,
    "Longitude": -2.9319666666666664,
    "Altitude": "210.6 metres",
    "City": "Dockray",
    "State": "England",
    "Country": "United Kingdom",
    "CountryCode": "GB",
    "DisplayName": "Park Brow, Matterdale, Dockray, Westmorland and Furness, England, CA11 0JY, United Kingdom",
    "Region": "Westmorland and Furness",
    "CameraMake": "Apple",
    "CameraModel": "iPhone 15 Pro",
    "LensModel": "iPhone 15 Pro back triple camera 6.765mm f/1.78",
    "DateTaken": "2026:01:12 11:43:49",
    "ExposureTime": "1/842 sec",
    "FNumber": "f/1.8",
    "ISO": "80",
    "FocalLength": "6.8 mm",
    "Orientation": "Top, left side (Horizontal / normal)",
    "Software": "26.2",
    "OptimizedImages": {
      "WebPImage": "e59c22f3fe954af4.webp",
      "OriginalSize": 1341077,
      "OptimizedSize": 543812,
      "CompressionRatio": 59.44960654757333
    },
    "HasGpsData": true
  },
  {
    "FileName": "IMG_3071.JPEG",
    "FilePath": "IMG_3071.JPEG",
    "FileSize": 2362001,
    "Latitude": 54.57607222222222,
    "Longitude": -2.9319777777777776,
    "Altitude": "210.07 metres",
    "City": "Dockray",
    "State": "England",
    "Country": "United Kingdom",
    "CountryCode": "GB",
    "DisplayName": "Park Brow, Matterdale, Dockray, Westmorland and Furness, England, CA11 0JY, United Kingdom",
    "Region": "Westmorland and Furness",
    "CameraMake": "Apple",
    "CameraModel": "iPhone 15 Pro",
    "LensModel": "iPhone 15 Pro back triple camera 6.765mm f/1.78",
    "DateTaken": "2026:01:12 11:43:44",
    "ExposureTime": "1/121 sec",
    "FNumber": "f/1.8",
    "ISO": "80",
    "FocalLength": "6.8 mm",
    "Orientation": "Top, left side (Horizontal / normal)",
    "Software": "26.2",
    "OptimizedImages": {
      "WebPImage": "e56a5f1848192ac9.webp",
      "OriginalSize": 2362001,
      "OptimizedSize": 1172680,
      "CompressionRatio": 50.35226488049751
    },
    "HasGpsData": true
  }
]