[
  {
    "FileName": "IMG_3069.JPEG",
    "FilePath": "IMG_3069.JPEG",
    "FileSize": 989239,
    "Latitude": 51.178733333333334,
    "Longitude": -1.8266972222222222,
    "Altitude": "105 metres",
    "City": "West Amesbury",
    "State": "England",
    "Country": "United Kingdom",
    "CountryCode": "GB",
    "DisplayName": "Station Stone, A303, Amesbury, West Amesbury, Wiltshire, England, SP4 8NU, United Kingdom",
    "Region": "Wiltshire",
    "CameraMake": "Apple",
    "CameraModel": "iPhone 15 Pro",
    "LensModel": "iPhone 15 Pro back triple camera 6.765mm f/1.78",
    "DateTaken": "2026:01:11 11:25:08",
    "ExposureTime": "1/1560 sec",
    "FNumber": "f/1.8",
    "ISO": "80",
    "FocalLength": "6.8 mm",
    "Orientation": "Top, left side (Horizontal / normal)",
    "Software": "26.2",
    "OptimizedImages": {
      "WebPImage": "1f378f7043c17fae.webp",
      "OriginalSize": 989239,
      "OptimizedSize": 347106,
      "CompressionRatio": 64.9118160525414
    },
    "HasGpsData": true
  },
  {
    "FileName": "IMG_3068.JPEG",
    "FilePath": "IMG_3068.JPEG",
    "FileSize": 1073409,
    "Latitude": 51.178733333333334,
    "Longitude": -1.8267333333333333,
    "Altitude": "101.27 metres",
    "City": "West Amesbury",
    "State": "England",
    "Country": "United Kingdom",
    "CountryCode": "GB",
    "DisplayName": "Station Stone, A303, Amesbury, West Amesbury, Wiltshire, England, SP4 8NU, United Kingdom",
    "Region": "Wiltshire",
    "CameraMake": "Apple",
    "CameraModel": "iPhone 15 Pro",
    "LensModel": "iPhone 15 Pro back triple camera 6.765mm f/1.78",
    "DateTaken": "2026:01:11 11:25:04",
    "ExposureTime": "1/1560 sec",
    "FNumber": "f/1.8",
    "ISO": "80",
    "FocalLength": "6.8 mm",
    "Orientation": "Top, left side (Horizontal / normal)",
    "Software": "26.2",
    "OptimizedImages": {
      "WebPImage": "3552c8eeff550063.webp",
      "OriginalSize": 1073409,
      "OptimizedSize": 393612,
      "CompressionRatio": 63.33065960877913
    },
    "HasGpsData": true
  },
  {
    "FileName": "IMG_3063.JPEG",
    "FilePath": "IMG_3063.JPEG",
    "FileSize": 997202,
    "Latitude": 51.179183333333334,
    "Longitude": -1.8263805555555555,
    "Altitude": "100.69 metres",
    "City": "West Amesbury",
    "State": "England",
    "Country": "United Kingdom",
    "CountryCode": "GB",
    "DisplayName": "Station Stone, A303, Amesbury, West Amesbury, Wiltshire, England, SP4 8NU, United Kingdom",
    "Region": "Wiltshire",
    "CameraMake": "Apple",
    "CameraModel": "iPhone 15 Pro",
    "LensModel": "iPhone 15 Pro back triple camera 6.765mm f/1.78",
    "DateTaken": "2026:01:11 11:23:46",
    "ExposureTime": "1/1637 sec",
    "FNumber": "f/1.8",
    "ISO": "80",
    "FocalLength": "6.8 mm",
    "Orientation": "Top, left side (Horizontal / normal)",
    "Software": "26.2",
    "OptimizedImages": {
      "WebPImage": "a094e1226499157d.webp",
      "OriginalSize": 997202,
      "OptimizedSize": 367726,
      "CompressionRatio": 63.12422157195834
    },
    "HasGpsData": true
  },
  {
    "FileName": "IMG_3065.JPEG",
    "FilePath": "IMG_3065.JPEG",
    "FileSize": 1066748,
    "Latitude": 51.17908055555555,
    "Longitude": -1.826447222222222,
    "Altitude": "104.39 metres",
    "City": "West Amesbury",
    "State": "England",
    "Country": "United Kingdom",
    "CountryCode": "GB",
    "DisplayName": "Station Stone, A303, Amesbury, West Amesbury, Wiltshire, England, SP4 8NU, United Kingdom",
    "Region": "Wiltshire",
    "CameraMake": "Apple",
    "CameraModel": "iPhone 15 Pro",
    "LensModel": "iPhone 15 Pro back triple camera 6.765mm f/1.78",
    "DateTaken": "2026:01:11 11:24:11",
    "ExposureTime": "1/1524 sec",
    "FNumber": "f/1.8",
    "ISO": "80",
    "FocalLength": "6.8 mm",
    "Orientation": "Top, left side (Horizontal / normal)",
    "Software": "26.2",
    "OptimizedImages": {
      "WebPImage": "248fa38ce2db81d5.webp",
      "OriginalSize": 1066748,
      "OptimizedSize": 394676,
      "CompressionRatio": 63.001946101609754
    },
    "HasGpsData": true
  }
]